{
  "build_id": "3.9.9",
  "device_id": "3c458410ded6c6da1e28f0c9",
  "install_id": "2371d9e7-ba6a-47ee-8048-9d52d3c774a0",
  "machine_hash": "cfe6350ead72dd8319393a58afab54e1eebb4dbc0fdf546de7d2dcf1a659e185",
  "status": "active",
  "host": "craft.pe",
  "port": 19132,
  "game_version": "1.21.100",
  "bot_version": "3.9.9",
  "first_seen": "2026-03-30T14:51:49.443Z",
  "last_seen": "2026-04-01T14:38:50.139Z",
  "updated_at": "2026-04-01T14:38:50.139Z",
  "device": {
    "platform": "win32",
    "arch": "x64",
    "hostname": "lenovo",
    "release": "10.0.22000",
    "cpu": "Intel(R) Core(TM) i3-8100 CPU @ 3.60GHz",
    "cpu_count": 4,
    "ram_mb": 8060,
    "mac_count": 1
  }
}